MANIFEST.in
README.txt
setup.py
Products/__init__.py
Products/__init__.pyc
Products.Maps.egg-info/PKG-INFO
Products.Maps.egg-info/SOURCES.txt
Products.Maps.egg-info/dependency_links.txt
Products.Maps.egg-info/namespace_packages.txt
Products.Maps.egg-info/not-zip-safe
Products.Maps.egg-info/requires.txt
Products.Maps.egg-info/top_level.txt
Products/Maps/__init__.py
Products/Maps/adapters.py
Products/Maps/collection.zcml
Products/Maps/config.py
Products/Maps/configure.zcml
Products/Maps/field.py
Products/Maps/profiles.zcml
Products/Maps/setuphandlers.py
Products/Maps/validator.py
Products/Maps/browser/__init__.py
Products/Maps/browser/config.py
Products/Maps/browser/configure.zcml
Products/Maps/browser/controlpanel.py
Products/Maps/browser/map.py
Products/Maps/browser/maps_location.pt
Products/Maps/browser/maps_map.pt
Products/Maps/content/Location.py
Products/Maps/content/__init__.py
Products/Maps/interfaces/__init__.py
Products/Maps/interfaces/config.py
Products/Maps/interfaces/content.py
Products/Maps/interfaces/geolocation.py
Products/Maps/interfaces/map.py
Products/Maps/interfaces/marker.py
Products/Maps/locales/generated.pot
Products/Maps/locales/manual.pot
Products/Maps/locales/maps.pot
Products/Maps/locales/rebuild_i18n.sh
Products/Maps/locales/da/LC_MESSAGES/maps.po
Products/Maps/locales/de/LC_MESSAGES/maps.po
Products/Maps/locales/el/LC_MESSAGES/maps.po
Products/Maps/locales/en/LC_MESSAGES/maps.po
Products/Maps/locales/es/LC_MESSAGES/maps.po
Products/Maps/locales/fi/LC_MESSAGES/maps.po
Products/Maps/locales/fr/LC_MESSAGES/maps.po
Products/Maps/locales/it/LC_MESSAGES/maps.po
Products/Maps/locales/ja/LC_MESSAGES/maps.po
Products/Maps/locales/nl/LC_MESSAGES/maps.mo
Products/Maps/locales/nl/LC_MESSAGES/maps.po
Products/Maps/locales/no/LC_MESSAGES/maps.po
Products/Maps/locales/zh_TW/LC_MESSAGES/maps.po
Products/Maps/profiles/default/Products.map_various.txt
Products/Maps/profiles/default/controlpanel.xml
Products/Maps/profiles/default/cssregistry.xml
Products/Maps/profiles/default/factorytool.xml
Products/Maps/profiles/default/jsregistry.xml
Products/Maps/profiles/default/metadata.xml
Products/Maps/profiles/default/propertiestool.xml
Products/Maps/profiles/default/rolemap.xml
Products/Maps/profiles/default/skins.xml
