Metadata-Version: 1.0
Name: Products.Maps
Version: 3.3
Summary: A simple, easy to use Plone integration with Google Maps
Home-page: http://plone.org/products/maps
Author: Florian Schulze
Author-email: fschulze@jarn.com
License: GPL
Keywords: Google Maps Zope Plone
Platform: UNKNOWN
Classifier: Framework :: Zope2
Classifier: Framework :: Plone
Classifier: Framework :: Plone :: 3.3
Classifier: Framework :: Plone :: 4.0
Classifier: Framework :: Plone :: 4.1
Classifier: Framework :: Plone :: 4.2
Classifier: Framework :: Plone :: 4.3
Classifier: License :: OSI Approved :: GNU General Public License (GPL)
Classifier: Programming Language :: Python
